rocket/__init__.py
rocket/rocket.py
haithoum21-1.0.3.dist-info/LICENSE.txt
haithoum21-1.0.3.dist-info/METADATA
haithoum21-1.0.3.dist-info/WHEEL
haithoum21-1.0.3.dist-info/top_level.txt
haithoum21-1.0.3.dist-info/RECORD
