Metadata-Version: 2.1
Name: haithoum21
Version: 1.0.3
Summary: An awesome package that does something
Home-page: http://pypi.python.org/pypi/rocket/
Author: Haitham
Author-email: haithambadereddine.dz@gmail.com
License: LICENSE.txt
License-File: LICENSE.txt
Requires-Dist: rocket
